englishexelog.py
englishexelog-0.0.1.dist-info/METADATA
englishexelog-0.0.1.dist-info/WHEEL
englishexelog-0.0.1.dist-info/top_level.txt
englishexelog-0.0.1.dist-info/RECORD
