Metadata-Version: 2.1
Name: englishexelog
Version: 0.0.1
Summary: A simple logging module!
Author-email: Englishexe <englishexe8910@gmail.com>
Classifier: Programming Language :: Python :: 3
Classifier: License :: OSI Approved :: MIT License
Classifier: Operating System :: OS Independent
Requires-Python: >=3.7
